PythonProject/__init__.py
PythonProject/area.py
area_calc_test-0.0.1.dist-info/METADATA
area_calc_test-0.0.1.dist-info/WHEEL
area_calc_test-0.0.1.dist-info/top_level.txt
area_calc_test-0.0.1.dist-info/RECORD
