Metadata-Version: 2.4
Name: area_calc_test
Version: 0.0.1
Summary: This is the simplest module for calculation square of input figure.
Home-page: http://wubbalubba/area_function
Author: fominaav
Author-email: fomina.av@phystech.edu
Project-URL: GitHub, https://github.com/vvubbalubbab
Keywords: files speedfiles
Classifier: Programming Language :: Python :: 3.11
Classifier: License :: OSI Approved :: MIT License
Classifier: Operating System :: OS Independent
Requires-Python: >=3.6
Requires-Dist: requests>=2.25.1
Dynamic: author
Dynamic: author-email
Dynamic: classifier
Dynamic: description
Dynamic: description-content-type
Dynamic: home-page
Dynamic: keywords
Dynamic: project-url
Dynamic: requires-dist
Dynamic: requires-python
Dynamic: summary
